gents/__init__.py
gents/hfcollection.py
gents/meta.py
gents/timeseries.py
gents/utils.py
gents/tests/test_case_files.py
gents/tests/test_cases.py
gents/tests/test_dask.py
gents/tests/test_hfcollection.py
gents/tests/test_tscollection.py
gents/tests/test_utils.py
gents/tests/test_workflow.py
gents-0.9.3.dist-info/licenses/LICENSE
gents-0.9.3.dist-info/METADATA
gents-0.9.3.dist-info/WHEEL
gents-0.9.3.dist-info/top_level.txt
gents-0.9.3.dist-info/RECORD
