Metadata-Version: 2.4
Name: GenTS
Version: 0.9.3
Summary: A useful tool for post-processing Earth System Model output 'history files' into the time series format.
Author-email: Cameron Cummins <cameron.cummins@utexas.edu>
Project-URL: Homepage, https://github.com/AgentOxygen/GenTS
Project-URL: Issues, https://github.com/AgentOxygen/GenTS
Classifier: Programming Language :: Python :: 3
Classifier: License :: OSI Approved :: MIT License
Classifier: Operating System :: OS Independent
Requires-Python: >=3.10.13
License-File: LICENSE
Requires-Dist: numpy
Requires-Dist: netcdf4
Requires-Dist: cftime
Provides-Extra: parallel
Requires-Dist: dask[distributed]; extra == "parallel"
Dynamic: license-file
